gomaths/__init__.py
gomaths/base.py
gomaths/gomaths.py
gomaths-0.0.1.dist-info/METADATA
gomaths-0.0.1.dist-info/WHEEL
gomaths-0.0.1.dist-info/top_level.txt
gomaths-0.0.1.dist-info/RECORD
