Metadata-Version: 2.1
Name: gomaths
Version: 0.0.1
Summary: A simple package of mathematics(beta test)
Home-page: https://github.com/soso080/gomaths
Author: Soso
Author-email: soribasoriba94@gmail.com
Classifier: Programming Language :: Python :: 3
Classifier: License :: OSI Approved :: MIT License
Classifier: Operating System :: OS Independent
Requires-Python: >=3.6
